{
"type": "FeatureCollection",
"name": "security",
"crs": { "type": "name", "properties": { "name": "urn:ogc:def:crs:OGC:1.3:CRS84" } },
"features": [
{ "type": "Feature", "properties": { "ward": 3, "Tole": "DUGUNA", "latitude": 27.926386090499999, "longitude": 85.9349537274, "Institutio": "Security Institution", "Name": "APF Check Post", "Insti_nep": ";'/Iff lgsfo", "Nep_Name": "PlkPkm r]s kf]i6" }, "geometry": { "type": "Point", "coordinates": [ 85.934953727413983, 27.92638609048549 ] } },
{ "type": "Feature", "properties": { "ward": 2, "Tole": "Chaukidada", "latitude": 27.9586866, "longitude": 85.9551586, "Institutio": "Security Institution", "Name": "Illaka Police Station", "Insti_nep": ";'/Iff lgsfo", "Nep_Name": "O{nfsf k|x/L sfof{no" }, "geometry": { "type": "Point", "coordinates": [ 85.9551586, 27.9586866 ] } },
{ "type": "Feature", "properties": { "ward": 4, "Tole": "Naranthan", "latitude": 27.8902952, "longitude": 85.9258103, "Institutio": "Security Institution", "Name": "Phulpingkati Prahari Chauki", "Insti_nep": ";'/Iff lgsfo", "Nep_Name": "km'lNkªs§L k|x/L rf}sL" }, "geometry": { "type": "Point", "coordinates": [ 85.9258103, 27.8902952 ] } }
]
}
